GDAL_VERSION
MANIFEST.in
README.rst
setup.py
./osgeo_utils/__init__.py
./osgeo_utils/gdal2tiles.py
./osgeo_utils/gdal2xyz.py
./osgeo_utils/gdal_calc.py
./osgeo_utils/gdal_edit.py
./osgeo_utils/gdal_fillnodata.py
./osgeo_utils/gdal_merge.py
./osgeo_utils/gdal_pansharpen.py
./osgeo_utils/gdal_polygonize.py
./osgeo_utils/gdal_proximity.py
./osgeo_utils/gdal_retile.py
./osgeo_utils/gdal_sieve.py
./osgeo_utils/gdalattachpct.py
./osgeo_utils/gdalcompare.py
./osgeo_utils/gdalmove.py
./osgeo_utils/ogrmerge.py
./osgeo_utils/pct2rgb.py
./osgeo_utils/rgb2pct.py
./osgeo_utils/auxiliary/__init__.py
./osgeo_utils/auxiliary/array_util.py
./osgeo_utils/auxiliary/base.py
./osgeo_utils/auxiliary/batch_creator.py
./osgeo_utils/auxiliary/color_palette.py
./osgeo_utils/auxiliary/color_table.py
./osgeo_utils/auxiliary/extent_util.py
./osgeo_utils/auxiliary/gdal_argparse.py
./osgeo_utils/auxiliary/numpy_util.py
./osgeo_utils/auxiliary/osr_util.py
./osgeo_utils/auxiliary/progress.py
./osgeo_utils/auxiliary/raster_creation.py
./osgeo_utils/auxiliary/rectangle.py
./osgeo_utils/auxiliary/util.py
./osgeo_utils/samples/__init__.py
./osgeo_utils/samples/assemblepoly.py
./osgeo_utils/samples/build_jp2_from_xml.py
./osgeo_utils/samples/classify.py
./osgeo_utils/samples/crs2crs2grid.py
./osgeo_utils/samples/densify.py
./osgeo_utils/samples/dump_jp2.py
./osgeo_utils/samples/epsg_tr.py
./osgeo_utils/samples/esri2wkt.py
./osgeo_utils/samples/fft.py
./osgeo_utils/samples/fix_gpkg.py
./osgeo_utils/samples/gcps2ogr.py
./osgeo_utils/samples/gcps2vec.py
./osgeo_utils/samples/gcps2wld.py
./osgeo_utils/samples/gdal2grd.py
./osgeo_utils/samples/gdal_auth.py
./osgeo_utils/samples/gdal_cp.py
./osgeo_utils/samples/gdal_create_pdf.py
./osgeo_utils/samples/gdal_ls.py
./osgeo_utils/samples/gdal_lut.py
./osgeo_utils/samples/gdal_mkdir.py
./osgeo_utils/samples/gdal_remove_towgs84.py
./osgeo_utils/samples/gdal_rm.py
./osgeo_utils/samples/gdal_rmdir.py
./osgeo_utils/samples/gdal_vrtmerge.py
pygdal_chm.egg-info/PKG-INFO
pygdal_chm.egg-info/SOURCES.txt
pygdal_chm.egg-info/dependency_links.txt
pygdal_chm.egg-info/not-zip-safe
pygdal_chm.egg-info/requires.txt
pygdal_chm.egg-info/top_level.txt